pysmashgg/__init__.py
pysmashgg/api.py
pysmashgg/b_queries.py
pysmashgg/brackets.py
pysmashgg/e_queries.py
pysmashgg/events.py
pysmashgg/exceptions.py
pysmashgg/filters.py
pysmashgg/l_queries.py
pysmashgg/leagues.py
pysmashgg/p_queries.py
pysmashgg/players.py
pysmashgg/smashgg.py
pysmashgg/t_queries.py
pysmashgg/tournaments.py
tests/__init__.py
tests/tests.py
pysmashgg-1.2.0.1.dist-info/LICENSE.md
pysmashgg-1.2.0.1.dist-info/METADATA
pysmashgg-1.2.0.1.dist-info/WHEEL
pysmashgg-1.2.0.1.dist-info/top_level.txt
pysmashgg-1.2.0.1.dist-info/RECORD
