Metadata-Version: 2.1
Name: pysmashgg
Version: 1.2.0.1
Summary: Python Wrapper for smash.gg's GraphQL API
Home-page: https://github.com/JeremySkalla/SmashGGPythonWrapper
Author: Jeremy Skalla
Author-email: jthroughs@gmail.com
Classifier: Programming Language :: Python :: 3.9
Classifier: License :: OSI Approved :: MIT License
Classifier: Operating System :: OS Independent
Requires-Python: >=3.6
License-File: LICENSE.md
Requires-Dist: requests
